{
  "name": "GBOV",
  "delimiter": ";",
  "comment_char": "#",
  "regex": "^GBOV__(.*?)__(.*?)__([0-9]{8}T[0-9]{6}Z)__([0-9]{8}T[0-9]{6}Z)\\.csv$",
  "longitude_name": "Lon_IS",
  "latitude_name": "Lat_IS",
  "time_name": "TIME_IS",
  "time_format": "yyyyMMdd'T'HHmmssX",
  "location_from_station_database": true,
  "variables": [
    { "name": "TIME_IS", "type": "int", "units": "s", "long_name": "", "cf_standard": "" },
    { "name": "FIPAR_down", "type": "float", "fill_value": -999.0, "units": "", "long_name": "", "cf_standard": "" },
    { "name": "FIPAR_down_err", "type": "float", "fill_value": -999.0, "units": "", "long_name": "", "cf_standard": "" },
    { "name": "FIPAR_total", "type": "float", "fill_value": -999.0, "units": "", "long_name": "", "cf_standard": "" },
    { "name": "FIPAR_total_err", "type": "float", "fill_value": -999.0, "units": "", "long_name": "", "cf_standard": "" },
    { "name": "FIPAR_up", "type": "float", "fill_value": -999.0, "units": "", "long_name": "", "cf_standard": "" },
    { "name": "FIPAR_up_err", "type": "float", "fill_value": -999.0, "units": "", "long_name": "", "cf_standard": "" },
    { "name": "RM6_down_flag", "type": "short", "fill_value": -999, "units": "", "long_name": "", "cf_standard": "", "ancillary_variables": "down_flag" },
    { "name": "RM6_up_flag", "type": "short", "fill_value": -999, "units": "", "long_name": "", "cf_standard": "", "ancillary_variables": "up_flag" },
    { "name": "Clumping_Miller", "type": "float", "fill_value": -999.0, "units": "", "long_name": "", "cf_standard": "" },
    { "name": "Clumping_Miller_err", "type": "float", "fill_value": -999.0, "units": "", "long_name": "", "cf_standard": "" },
    { "name": "Clumping_Warren", "type": "float", "fill_value": -999.0, "units": "", "long_name": "", "cf_standard": "" },
    { "name": "Clumping_Warren_err", "type": "float", "fill_value": -999.0, "units": "", "long_name": "", "cf_standard": "" },
    { "name": "LAI_Miller_down", "type": "float", "fill_value": -999.0, "units": "", "long_name": "", "cf_standard": "" },
    { "name": "LAI_Miller_down_err", "type": "float", "fill_value": -999.0, "units": "", "long_name": "", "cf_standard": "" },
    { "name": "LAI_Miller_up", "type": "float", "fill_value": -999.0, "units": "", "long_name": "", "cf_standard": "" },
    { "name": "LAI_Miller_up_err", "type": "float", "fill_value": -999.0, "units": "", "long_name": "", "cf_standard": "" },
    { "name": "LAI_Warren_down", "type": "float", "fill_value": -999.0, "units": "", "long_name": "", "cf_standard": "" },
    { "name": "LAI_Warren_down_err", "type": "float", "fill_value": -999.0, "units": "", "long_name": "", "cf_standard": "" },
    { "name": "LAI_Warren_up", "type": "float", "fill_value": -999.0, "units": "", "long_name": "", "cf_standard": "" },
    { "name": "LAI_Warren_up_err", "type": "float", "fill_value": -999.0, "units": "", "long_name": "", "cf_standard": "" },
    { "name": "LAI_down", "type": "float", "fill_value": -999.0, "units": "", "long_name": "", "cf_standard": "" },
    { "name": "LAI_total_Miller", "type": "float", "fill_value": -999.0, "units": "", "long_name": "", "cf_standard": "" },
    { "name": "LAI_total_Warren", "type": "float", "fill_value": -999.0, "units": "", "long_name": "", "cf_standard": "" },
    { "name": "LAIe_Miller_down", "type": "float", "fill_value": -999.0, "units": "", "long_name": "", "cf_standard": "" },
    { "name": "LAIe_Miller_down_err", "type": "float", "fill_value": -999.0, "units": "", "long_name": "", "cf_standard": "" },
    { "name": "LAIe_Miller_up", "type": "float", "fill_value": -999.0, "units": "", "long_name": "", "cf_standard": "" },
    { "name": "LAIe_Miller_up_err", "type": "float", "fill_value": -999.0, "units": "", "long_name": "", "cf_standard": "" },
    { "name": "LAIe_Warren_down", "type": "float", "fill_value": -999.0, "units": "", "long_name": "", "cf_standard": "" },
    { "name": "LAIe_Warren_down_err", "type": "float", "fill_value": -999.0, "units": "", "long_name": "", "cf_standard": "" },
    { "name": "LAIe_Warren_up", "type": "float", "fill_value": -999.0, "units": "", "long_name": "", "cf_standard": "" },
    { "name": "LAIe_Warren_up_err", "type": "float", "fill_value": -999.0, "units": "", "long_name": "", "cf_standard": "" },
    { "name": "PAI_Miller", "type": "float", "fill_value": -999.0, "units": "", "long_name": "", "cf_standard": "" },
    { "name": "PAI_Miller_err", "type": "float", "fill_value": -999.0, "units": "", "long_name": "", "cf_standard": "" },
    { "name": "PAI_Warren", "type": "float", "fill_value": -999.0, "units": "", "long_name": "", "cf_standard": "" },
    { "name": "PAI_Warren_err", "type": "float", "fill_value": -999.0, "units": "", "long_name": "", "cf_standard": "" },
    { "name": "PAIe_Miller", "type": "float", "fill_value": -999.0, "units": "", "long_name": "", "cf_standard": "" },
    { "name": "PAIe_Miller_err", "type": "float", "fill_value": -999.0, "units": "", "long_name": "", "cf_standard": "" },
    { "name": "PAIe_Warren", "type": "float", "fill_value": -999.0, "units": "", "long_name": "", "cf_standard": "" },
    { "name": "PAIe_Warren_err", "type": "float", "fill_value": -999.0, "units": "", "long_name": "", "cf_standard": "" },
    { "name": "clumping_Miller_down", "type": "float", "fill_value": -999.0, "units": "", "long_name": "", "cf_standard": "" },
    { "name": "clumping_Miller_down_err", "type": "float", "fill_value": -999.0, "units": "", "long_name": "", "cf_standard": "" },
    { "name": "clumping_Miller_up", "type": "float", "fill_value": -999.0, "units": "", "long_name": "", "cf_standard": "" },
    { "name": "clumping_Miller_up_err", "type": "float", "fill_value": -999.0, "units": "", "long_name": "", "cf_standard": "" },
    { "name": "clumping_Warren_down", "type": "float", "fill_value": -999.0, "units": "", "long_name": "", "cf_standard": "" },
    { "name": "clumping_Warren_down_err", "type": "float", "fill_value": -999.0, "units": "", "long_name": "", "cf_standard": "" },
    { "name": "clumping_Warren_up", "type": "float", "fill_value": -999.0, "units": "", "long_name": "", "cf_standard": "" },
    { "name": "clumping_Warren_up_err", "type": "float", "fill_value": -999.0, "units": "", "long_name": "", "cf_standard": "" },
    { "name": "RM7_down_flag", "type": "short", "fill_value": -999, "units": "", "long_name": "", "cf_standard": "", "ancillary_variables": "down_flag" },
    { "name": "RM7_up_flag", "type": "short", "fill_value": -999, "units": "", "long_name": "", "cf_standard": "", "ancillary_variables": "up_flag" },
    { "name": "LSE", "type": "float", "fill_value": -999.0, "units": "", "long_name": "", "cf_standard": "" },
    { "name": "LSE_STD", "type": "float", "fill_value": -999.0, "units": "", "long_name": "", "cf_standard": "" },
    { "name": "LSR", "type": "float", "fill_value": -999.0, "units": "", "long_name": "", "cf_standard": "" },
    { "name": "LSR_STD", "type": "float", "fill_value": -999.0, "units": "", "long_name": "", "cf_standard": "" },
    { "name": "QC_LSE", "type": "short", "fill_value": -999, "units": "", "long_name": "", "cf_standard": "" },
    { "name": "QC_LSR", "type": "short", "fill_value": -999, "units": "", "long_name": "", "cf_standard": "" },
    { "name": "LST", "type": "float", "fill_value": -999.0, "units": "", "long_name": "", "cf_standard": "" },
    { "name": "LST_STD", "type": "float", "fill_value": -999.0, "units": "", "long_name": "", "cf_standard": "" },
    { "name": "QC_LST", "type": "short", "fill_value": -999, "units": "", "long_name": "", "cf_standard": "" },
    { "name": "QC_SM_5", "type": "short", "fill_value": -999, "units": "", "long_name": "", "cf_standard": "" },
    { "name": "SM_5", "type": "double", "fill_value": -999.0, "units": "", "long_name": "", "cf_standard": "" }
  ],
  "station_database": {
    "primary_id": "site",
    "secondary_id": "station",
    "variables": [
      { "origin": "s","name": "site", "type": "string", "units": "1", "long_name": "Insitu data measurement site"},
      { "origin": "s","name": "station", "type": "string", "units": "1", "cf_standard": "platform_name", "long_name": "Insitu data measurement station"},
      { "origin": "s","name": "elevation", "type": "float", "units": "m", "cf_standard": "height_above_mean_sea_level", "long_name": "Height_above_X\" means the vertical distance above the named surface X. \"Mean sea level\" means the time mean of sea surface elevation at a given location over an arbitrary period sufficient to eliminate the tidal signals."},
      { "origin": "s","name": "IGBP_class", "type": "string", "units": "1", "long_name": "International Geosphere–Biosphere Programme ecosystem surface classification"},
      { "origin": "s","name": "Lat_IS", "type": "float",  "units": "degree_north", "cf_standard": "latitude", "long_name": "Latitude is positive northward; its units of degree_north (or equivalent) indicate this explicitly. In a latitude-longitude system defined with respect to a rotated North Pole, the standard name of grid_latitude should be used instead of latitude. Grid latitude is positive in the grid-northward direction, but its units should be plain degree."},
      { "origin": "s","name": "Lon_IS", "type": "float", "units": "degree_east", "cf_standard": "longitude", "long_name": "Longitude is positive eastward; its units of degree_east (or equivalent) indicate this explicitly. In a latitude-longitude system defined with respect to a rotated North Pole, the standard name of grid_longitude should be used instead of longitude. Grid longitude is positive in the grid-eastward direction, but its units should be plain degree."}
    ],
    "stations": [
      ["Cumberland Plain","CumberlandPlain",25,"Evergreen Broadleaf",-33.615,150.723],
      ["Steigerwaldt Land Services","STEI_016",481,"Deciduous Broadleaf",45.5089416503906,-89.5863723754883],
      ["Steigerwaldt Land Services","STEI_005",481,"Deciduous Broadleaf",45.5089416503906,-89.5863723754883],
      ["Steigerwaldt Land Services","STEI_015",481,"Deciduous Broadleaf",45.5089416503906,-89.5863723754883],
      ["Steigerwaldt Land Services","STEI_004",481,"Deciduous Broadleaf",45.5089416503906,-89.5863723754883],
      ["Steigerwaldt Land Services","STEI_058",481,"Deciduous Broadleaf",45.5089416503906,-89.5863723754883],
      ["Steigerwaldt Land Services","STEI_014",481,"Deciduous Broadleaf",45.5089416503906,-89.5863723754883],
      ["Steigerwaldt Land Services","STEI_003",481,"Deciduous Broadleaf",45.5089416503906,-89.5863723754883],
      ["Steigerwaldt Land Services","STEI_046",481,"Deciduous Broadleaf",45.5089416503906,-89.5863723754883],
      ["Steigerwaldt Land Services","STEI_013",481,"Deciduous Broadleaf",45.5089416503906,-89.5863723754883],
      ["Steigerwaldt Land Services","STEI_002",481,"Deciduous Broadleaf",45.5089416503906,-89.5863723754883],
      ["Steigerwaldt Land Services","STEI_009",481,"Deciduous Broadleaf",45.5089416503906,-89.5863723754883],
      ["Steigerwaldt Land Services","STEI_019",481,"Deciduous Broadleaf",45.5089416503906,-89.5863723754883],
      ["Steigerwaldt Land Services","STEI_008",481,"Deciduous Broadleaf",45.5089416503906,-89.5863723754883],
      ["Steigerwaldt Land Services","STEI_007",481,"Deciduous Broadleaf",45.5089416503906,-89.5863723754883],
      ["Steigerwaldt Land Services","STEI_017",481,"Deciduous Broadleaf",45.5089416503906,-89.5863723754883],
      ["Steigerwaldt Land Services","STEI_006",481,"Deciduous Broadleaf",45.5089416503906,-89.5863723754883],
      ["Steigerwaldt Land Services","STEI_012",481,"Deciduous Broadleaf",45.5089416503906,-89.5863723754883],
      ["Steigerwaldt Land Services","STEI_001",481,"Deciduous Broadleaf",45.5089416503906,-89.5863723754883],
      ["Steigerwaldt Land Services","STEI_055",481,"Deciduous Broadleaf",45.5089416503906,-89.5863723754883],
      ["Steigerwaldt Land Services","STEI_022",481,"Deciduous Broadleaf",45.5089416503906,-89.5863723754883],
      ["Steigerwaldt Land Services","STEI_011",481,"Deciduous Broadleaf",45.5089416503906,-89.5863723754883],
      ["Steigerwaldt Land Services","STEI_021",481,"Deciduous Broadleaf",45.5089416503906,-89.5863723754883],
      ["Steigerwaldt Land Services","STEI_010",481,"Deciduous Broadleaf",45.5089416503906,-89.5863723754883],
      ["Condom","Smos3",174,"Croplands",43.9744,0.3361],
      ["Dead Lake","DELA_018",22,"Deciduous Broadleaf",32.54172,-87.80389],
      ["Dead Lake","DELA_007",22,"Deciduous Broadleaf",32.54172,-87.80389],
      ["Dead Lake","DELA_008",22,"Deciduous Broadleaf",32.54172,-87.80389],
      ["Dead Lake","DELA_016",22,"Deciduous Broadleaf",32.54172,-87.80389],
      ["Dead Lake","DELA_005",22,"Deciduous Broadleaf",32.54172,-87.80389],
      ["Dead Lake","DELA_017",22,"Deciduous Broadleaf",32.54172,-87.80389],
      ["Dead Lake","DELA_006",22,"Deciduous Broadleaf",32.54172,-87.80389],
      ["Dead Lake","DELA_014",22,"Deciduous Broadleaf",32.54172,-87.80389],
      ["Dead Lake","DELA_003",22,"Deciduous Broadleaf",32.54172,-87.80389],
      ["Dead Lake","DELA_015",22,"Deciduous Broadleaf",32.54172,-87.80389],
      ["Dead Lake","DELA_004",22,"Deciduous Broadleaf",32.54172,-87.80389],
      ["Dead Lake","DELA_012",22,"Deciduous Broadleaf",32.54172,-87.80389],
      ["Dead Lake","DELA_001",22,"Deciduous Broadleaf",32.54172,-87.80389],
      ["Dead Lake","DELA_046",22,"Deciduous Broadleaf",32.54172,-87.80389],
      ["Dead Lake","DELA_013",22,"Deciduous Broadleaf",32.54172,-87.80389],
      ["Dead Lake","DELA_002",22,"Deciduous Broadleaf",32.54172,-87.80389],
      ["Dead Lake","DELA_010",22,"Deciduous Broadleaf",32.54172,-87.80389],
      ["Dead Lake","DELA_044",22,"Deciduous Broadleaf",32.54172,-87.80389],
      ["Dead Lake","DELA_011",22,"Deciduous Broadleaf",32.54172,-87.80389],
      ["Dead Lake","DELA_053",22,"Deciduous Broadleaf",32.54172,-87.80389],
      ["Dead Lake","DELA_020",22,"Deciduous Broadleaf",32.54172,-87.80389],
      ["Dead Lake","DELA_051",22,"Deciduous Broadleaf",32.54172,-87.80389],
      ["Dead Lake","DELA_009",22,"Deciduous Broadleaf",32.54172,-87.80389],
      ["Wustebach","Wustebach",610,"Evergreen Needleleaf Forest",50.50493,6.3309627],
      ["Southern Great Plains","SouthernGreatPlains",318,"Croplands",36.60575,-97.48876],
      ["Gobabeb","Gobabeb",407,"Bare soil and Rocks",-23.5618361,15.0413138888889],
      ["Niwot Ridge Mountain Research Station","NIWO_060",3050,"Evergreen Needleleaf",40.0543,-105.58245],
      ["Niwot Ridge Mountain Research Station","NIWO_048",3050,"Evergreen Needleleaf",40.0543,-105.58245],
      ["Niwot Ridge Mountain Research Station","NIWO_056",3050,"Evergreen Needleleaf",40.0543,-105.58245],
      ["Niwot Ridge Mountain Research Station","NIWO_054",3050,"Evergreen Needleleaf",40.0543,-105.58245],
      ["Bartlett Experimental Forest","BART_018",232,"Mixed Forest",44.063901,-71.287308],
      ["Bartlett Experimental Forest","BART_007",232,"Mixed Forest",44.063901,-71.287308],
      ["Bartlett Experimental Forest","BART_028",232,"Mixed Forest",44.063901,-71.287308],
      ["Bartlett Experimental Forest","BART_006",232,"Mixed Forest",44.063901,-71.287308],
      ["Bartlett Experimental Forest","BART_034",232,"Mixed Forest",44.063901,-71.287308],
      ["Bartlett Experimental Forest","BART_023",232,"Mixed Forest",44.063901,-71.287308],
      ["Bartlett Experimental Forest","BART_012",232,"Mixed Forest",44.063901,-71.287308],
      ["Bartlett Experimental Forest","BART_001",232,"Mixed Forest",44.063901,-71.287308],
      ["Bartlett Experimental Forest","BART_011",232,"Mixed Forest",44.063901,-71.287308],
      ["Bartlett Experimental Forest","BART_010",232,"Mixed Forest",44.063901,-71.287308],
      ["Bartlett Experimental Forest","BART_027",232,"Mixed Forest",44.063901,-71.287308],
      ["Bartlett Experimental Forest","BART_016",232,"Mixed Forest",44.063901,-71.287308],
      ["Bartlett Experimental Forest","BART_005",232,"Mixed Forest",44.063901,-71.287308],
      ["Bartlett Experimental Forest","BART_026",232,"Mixed Forest",44.063901,-71.287308],
      ["Bartlett Experimental Forest","BART_015",232,"Mixed Forest",44.063901,-71.287308],
      ["Bartlett Experimental Forest","BART_004",232,"Mixed Forest",44.063901,-71.287308],
      ["Bartlett Experimental Forest","BART_047",232,"Mixed Forest",44.063901,-71.287308],
      ["Bartlett Experimental Forest","BART_025",232,"Mixed Forest",44.063901,-71.287308],
      ["Bartlett Experimental Forest","BART_003",232,"Mixed Forest",44.063901,-71.287308],
      ["Bartlett Experimental Forest","BART_024",232,"Mixed Forest",44.063901,-71.287308],
      ["Bartlett Experimental Forest","BART_013",232,"Mixed Forest",44.063901,-71.287308],
      ["Bartlett Experimental Forest","BART_002",232,"Mixed Forest",44.063901,-71.287308],
      ["Bartlett Experimental Forest","BART_041",232,"Mixed Forest",44.063901,-71.287308],
      ["Pezenas","Smos10",30,"Croplands",43.43833,3.40333],
      ["North Sterling","STER_032",1364,"Grasslands",40.461952,-103.02934],
      ["North Sterling","STER_033",1364,"Grasslands",40.461952,-103.02934],
      ["North Sterling","STER_031",1364,"Grasslands",40.461952,-103.02934],
      ["North Sterling","STER_009",1364,"Grasslands",40.461952,-103.02934],
      ["North Sterling","STER_014",1364,"Grasslands",40.461952,-103.02934],
      ["North Sterling","STER_026",1364,"Grasslands",40.461952,-103.02934],
      ["North Sterling","STER_034",1364,"Grasslands",40.461952,-103.02934],
      ["North Sterling","STER_035",1364,"Grasslands",40.461952,-103.02934],
      ["North Sterling","STER_029",1364,"Grasslands",40.461952,-103.02934],
      ["North Sterling","STER_018",1364,"Grasslands",40.461952,-103.02934],
      ["North Sterling","STER_008",1364,"Grasslands",40.461952,-103.02934],
      ["North Sterling","STER_027",1364,"Grasslands",40.461952,-103.02934],
      ["North Sterling","STER_005",1364,"Grasslands",40.461952,-103.02934],
      ["North Sterling","STER_028",1364,"Grasslands",40.461952,-103.02934],
      ["North Sterling","STER_006",1364,"Grasslands",40.461952,-103.02934],
      ["Tateno","Tateno",25,"Urban and Built-up",36.05918,140.12444],
      ["Watkinsville","SSE",216,"Grassland",33.78,-83.39],
      ["Wicken Fen","WickenFen",46,"Croplands",52.3094,0.27972],
      ["Desert Rock","Desert_Rock_NV",1007,"Open Shrublands",36.62418,-116.0199],
      ["Hohes Holz","DE-HoH_CP03",129,"Deciduous Broadleaf Forest",52.08656,11.22235],
      ["Hohes Holz","DE-HoH_CP04",129,"Deciduous Broadleaf Forest",52.08656,11.22235],
      ["Hohes Holz","DE-HoH_CP01",129,"Deciduous Broadleaf Forest",52.08656,11.22235],
      ["Hohes Holz","DE-HoH_CP02",129,"Deciduous Broadleaf Forest",52.08656,11.22235],
      ["Hohes Holz","DE-HoH_CP05",129,"Deciduous Broadleaf Forest",52.08656,11.22235],
      ["Great Western Woodland","GreatWesternWoodland",448,"Open Shrublands",-30.192,120.654],
      ["Jones Ecological Research Center","JERC_054",44,"Evergreen Needleleaf",31.1948394775391,-84.468777],
      ["Jones Ecological Research Center","JERC_050",44,"Evergreen Needleleaf",31.1948394775391,-84.468777],
      ["Jones Ecological Research Center","JERC_062",44,"Evergreen Needleleaf",31.1948394775391,-84.468777],
      ["Jones Ecological Research Center","JERC_060",44,"Evergreen Needleleaf",31.1948394775391,-84.468777],
      ["Yanco","y9",119,"Grasslands",-35.0053482055664,146.309875488281],
      ["Yanco","Yanco",119,"Grasslands",-35.0053482055664,146.309875488281],
      ["Yanco","y1",119,"Grasslands",-35.0053482055664,146.309875488281],
      ["Yanco","y11",119,"Grasslands",-35.0053482055664,146.309875488281],
      ["Yanco","y2",119,"Grasslands",-35.0053482055664,146.309875488281],
      ["Yanco","y10",119,"Grasslands",-35.0053482055664,146.309875488281],
      ["Yanco","y3",119,"Grasslands",-35.0053482055664,146.309875488281],
      ["Yanco","y13",119,"Grasslands",-35.0053482055664,146.309875488281],
      ["Yanco","y4",119,"Grasslands",-35.0053482055664,146.309875488281],
      ["Yanco","y12",119,"Grasslands",-35.0053482055664,146.309875488281],
      ["Yanco","y5",119,"Grasslands",-35.0053482055664,146.309875488281],
      ["Yanco","y6",119,"Grasslands",-35.0053482055664,146.309875488281],
      ["Yanco","y7",119,"Grasslands",-35.0053482055664,146.309875488281],
      ["Yanco","y8",119,"Grasslands",-35.0053482055664,146.309875488281],
      ["Tibetian Plateau (Naqu)","NAQU2",4591,"Grasslands",31.31,91.82],
      ["Tibetian Plateau (Naqu)","NAQU1",4591,"Grasslands",31.31,91.82],
      ["Tibetian Plateau (Naqu)","NAQU4",4591,"Grasslands",31.31,91.82],
      ["Tibetian Plateau (Naqu)","NAQU3",4591,"Grasslands",31.31,91.82],
      ["Tibetian Plateau (Naqu)","NAQU5",4591,"Grasslands",31.31,91.82],
      ["Soaproot Saddle","SOAP_019",905,"Evergreen Needleleaf Forest",37.03337,-119.26219],
      ["Soaproot Saddle","SOAP_008",905,"Evergreen Needleleaf Forest",37.03337,-119.26219],
      ["Soaproot Saddle","SOAP_009",905,"Evergreen Needleleaf Forest",37.03337,-119.26219],
      ["Soaproot Saddle","SOAP_015",905,"Evergreen Needleleaf Forest",37.03337,-119.26219],
      ["Soaproot Saddle","SOAP_004",905,"Evergreen Needleleaf Forest",37.03337,-119.26219],
      ["Soaproot Saddle","SOAP_016",905,"Evergreen Needleleaf Forest",37.03337,-119.26219],
      ["Soaproot Saddle","SOAP_005",905,"Evergreen Needleleaf Forest",37.03337,-119.26219],
      ["Soaproot Saddle","SOAP_017",905,"Evergreen Needleleaf Forest",37.03337,-119.26219],
      ["Soaproot Saddle","SOAP_006",905,"Evergreen Needleleaf Forest",37.03337,-119.26219],
      ["Soaproot Saddle","SOAP_018",905,"Evergreen Needleleaf Forest",37.03337,-119.26219],
      ["Soaproot Saddle","SOAP_007",905,"Evergreen Needleleaf Forest",37.03337,-119.26219],
      ["Soaproot Saddle","SOAP_011",905,"Evergreen Needleleaf Forest",37.03337,-119.26219],
      ["Soaproot Saddle","SOAP_012",905,"Evergreen Needleleaf Forest",37.03337,-119.26219],
      ["Soaproot Saddle","SOAP_001",905,"Evergreen Needleleaf Forest",37.03337,-119.26219],
      ["Soaproot Saddle","SOAP_013",905,"Evergreen Needleleaf Forest",37.03337,-119.26219],
      ["Soaproot Saddle","SOAP_002",905,"Evergreen Needleleaf Forest",37.03337,-119.26219],
      ["Soaproot Saddle","SOAP_058",905,"Evergreen Needleleaf Forest",37.03337,-119.26219],
      ["Soaproot Saddle","SOAP_047",905,"Evergreen Needleleaf Forest",37.03337,-119.26219],
      ["Soaproot Saddle","SOAP_003",905,"Evergreen Needleleaf Forest",37.03337,-119.26219],
      ["Soaproot Saddle","SOAP_020",905,"Evergreen Needleleaf Forest",37.03337,-119.26219],
      ["Soaproot Saddle","SOAP_054",905,"Evergreen Needleleaf Forest",37.03337,-119.26219],
      ["Soaproot Saddle","SOAP_021",905,"Evergreen Needleleaf Forest",37.03337,-119.26219],
      ["Soaproot Saddle","SOAP_010",905,"Evergreen Needleleaf Forest",37.03337,-119.26219],
      ["Onaqui Ault","ONAQ_009",1685,"Open Shrublands",40.1775894165039,-112.452438354492],
      ["Onaqui Ault","ONAQ_019",1685,"Open Shrublands",40.1775894165039,-112.452438354492],
      ["Onaqui Ault","ONAQ_008",1685,"Open Shrublands",40.1775894165039,-112.452438354492],
      ["Onaqui Ault","ONAQ_018",1685,"Open Shrublands",40.1775894165039,-112.452438354492],
      ["Onaqui Ault","ONAQ_007",1685,"Open Shrublands",40.1775894165039,-112.452438354492],
      ["Onaqui Ault","ONAQ_017",1685,"Open Shrublands",40.1775894165039,-112.452438354492],
      ["Onaqui Ault","ONAQ_016",1685,"Open Shrublands",40.1775894165039,-112.452438354492],
      ["Onaqui Ault","ONAQ_005",1685,"Open Shrublands",40.1775894165039,-112.452438354492],
      ["Onaqui Ault","ONAQ_015",1685,"Open Shrublands",40.1775894165039,-112.452438354492],
      ["Onaqui Ault","ONAQ_004",1685,"Open Shrublands",40.1775894165039,-112.452438354492],
      ["Onaqui Ault","ONAQ_069",1685,"Open Shrublands",40.1775894165039,-112.452438354492],
      ["Onaqui Ault","ONAQ_025",1685,"Open Shrublands",40.1775894165039,-112.452438354492],
      ["Onaqui Ault","ONAQ_014",1685,"Open Shrublands",40.1775894165039,-112.452438354492],
      ["Onaqui Ault","ONAQ_003",1685,"Open Shrublands",40.1775894165039,-112.452438354492],
      ["Onaqui Ault","ONAQ_002",1685,"Open Shrublands",40.1775894165039,-112.452438354492],
      ["Onaqui Ault","ONAQ_023",1685,"Open Shrublands",40.1775894165039,-112.452438354492],
      ["Onaqui Ault","ONAQ_012",1685,"Open Shrublands",40.1775894165039,-112.452438354492],
      ["Onaqui Ault","ONAQ_011",1685,"Open Shrublands",40.1775894165039,-112.452438354492],
      ["Onaqui Ault","ONAQ_021",1685,"Open Shrublands",40.1775894165039,-112.452438354492],
      ["Onaqui Ault","ONAQ_010",1685,"Open Shrublands",40.1775894165039,-112.452438354492],
      ["Onaqui Ault","ONAQ_020",1685,"Open Shrublands",40.1775894165039,-112.452438354492],
      ["Onaqui Ault","ONAQ_051",1685,"Open Shrublands",40.1775894165039,-112.452438354492],
      ["Onaqui Ault","ONAQ_060",1685,"Open Shrublands",40.1775894165039,-112.452438354492],
      ["Mouthoumet","Smos7",538,"Croplands",42.96,2.53],
      ["Kyeamba","k2",437,"Croplands",-35.4932,147.559],
      ["Kyeamba","k5",437,"Croplands",-35.4932,147.559],
      ["Kyeamba","k11",437,"Croplands",-35.4932,147.559],
      ["Kyeamba","k6",437,"Croplands",-35.4932,147.559],
      ["Kyeamba","k10",437,"Croplands",-35.4932,147.559],
      ["Kyeamba","k7",437,"Croplands",-35.4932,147.559],
      ["Kyeamba","k13",437,"Croplands",-35.4932,147.559],
      ["Kyeamba","k12",437,"Croplands",-35.4932,147.559],
      ["Kyeamba","k14",437,"Croplands",-35.4932,147.559],
      ["Sioux Falls SurfRad","Sioux_Falls_SD",473,"Croplands",43.7340316772461,-96.62331],
      ["Barrow","Barrow",11,"Snow and Ice",71.3231,-156.61052],
      ["Saskatchewan","SK1",574,"Croplands",51.3347,-106.5647],
      ["Saskatchewan","SK3",574,"Croplands",51.3347,-106.5647],
      ["Saskatchewan","SK2",574,"Croplands",51.3347,-106.5647],
      ["Saskatchewan","SK4",574,"Croplands",51.3347,-106.5647],
      ["Valencia Anchor Station","v6",813,"Cropland Mosaics",39.5707206726074,-1.28822004795074],
      ["Valencia Anchor Station","v7",813,"Cropland Mosaics",39.5707206726074,-1.28822004795074],
      ["Valencia Anchor Station","v8",813,"Cropland Mosaics",39.5707206726074,-1.28822004795074],
      ["Valencia Anchor Station","v9",813,"Cropland Mosaics",39.5707206726074,-1.28822004795074],
      ["Valencia Anchor Station","v1",813,"Cropland Mosaics",39.5707206726074,-1.28822004795074],
      ["Valencia Anchor Station","v2",813,"Cropland Mosaics",39.5707206726074,-1.28822004795074],
      ["Valencia Anchor Station","v3",813,"Cropland Mosaics",39.5707206726074,-1.28822004795074],
      ["Valencia Anchor Station","v4",813,"Cropland Mosaics",39.5707206726074,-1.28822004795074],
      ["Valencia Anchor Station","v5",813,"Cropland Mosaics",39.5707206726074,-1.28822004795074],
      ["Yosemite Village","YosemiteVillage",2081,"Evergreen Needleleaf",37.7588889,-119.8211],
      ["Danube mega farme 1 Calarasi","Ca1",20,"Croplands",44.2057,27.3385],
      ["Table Mountain","Boulder_CO",1689,"Bare soil and Rocks",40.1249809265137,-105.236801147461],
      ["Rock Springs","Penn_State_PA",376,"Deciduous Broadleaf",40.7201194763184,-77.9308471679688],
      ["Manhattan","m1",347,"Grasslands",39.10274,-96.60974],
      ["Manhattan","Manhattan",347,"Grasslands",39.10274,-96.60974],
      ["Rosiorii de Vede","RdV1",102,"Croplands",44.10711,24.97872],
      ["Manitoba","MB6",272,"Croplands",49.56222,-98.01916],
      ["Manitoba","MB5",272,"Croplands",49.56222,-98.01916],
      ["Manitoba","MB8",272,"Croplands",49.56222,-98.01916],
      ["Manitoba","MB7",272,"Croplands",49.56222,-98.01916],
      ["Manitoba","MB13",272,"Croplands",49.56222,-98.01916],
      ["Manitoba","MB9",272,"Croplands",49.56222,-98.01916],
      ["Manitoba","MB12",272,"Croplands",49.56222,-98.01916],
      ["Manitoba","MB11",272,"Croplands",49.56222,-98.01916],
      ["Manitoba","MB10",272,"Croplands",49.56222,-98.01916],
      ["Manitoba","MB2",272,"Croplands",49.56222,-98.01916],
      ["Manitoba","MB1",272,"Croplands",49.56222,-98.01916],
      ["Manitoba","MB4",272,"Croplands",49.56222,-98.01916],
      ["Manitoba","MB3",272,"Croplands",49.56222,-98.01916],
      ["Cabauw","Cabauw",0,"Cropland Mosaics",51.9710006713867,4.92700004577637],
      ["Moab","MOAB_061",1767,"Open Shrublands",38.24836,-109.38831],
      ["Moab","MOAB_070",1767,"Open Shrublands",38.24836,-109.38831],
      ["Moab","MOAB_049",1767,"Open Shrublands",38.24836,-109.38831],
      ["Smithsonian Conservation Biology Institute","SCBI_008",361,"Mixed Forest",38.8929214477539,-78.1395034790039],
      ["Smithsonian Conservation Biology Institute","SCBI_010",361,"Mixed Forest",38.8929214477539,-78.1395034790039],
      ["Smithsonian Conservation Biology Institute","SCBI_063",361,"Mixed Forest",38.8929214477539,-78.1395034790039],
      ["Smithsonian Conservation Biology Institute","SCBI_062",361,"Mixed Forest",38.8929214477539,-78.1395034790039],
      ["Smithsonian Conservation Biology Institute","SCBI_014",361,"Mixed Forest",38.8929214477539,-78.1395034790039],
      ["Smithsonian Conservation Biology Institute","SCBI_003",361,"Mixed Forest",38.8929214477539,-78.1395034790039],
      ["Smithsonian Conservation Biology Institute","SCBI_035",361,"Mixed Forest",38.8929214477539,-78.1395034790039],
      ["Smithsonian Conservation Biology Institute","SCBI_013",361,"Mixed Forest",38.8929214477539,-78.1395034790039],
      ["Smithsonian Conservation Biology Institute","SCBI_002",361,"Mixed Forest",38.8929214477539,-78.1395034790039],
      ["Smithsonian Conservation Biology Institute","SCBI_034",361,"Mixed Forest",38.8929214477539,-78.1395034790039],
      ["Smithsonian Conservation Biology Institute","SCBI_012",361,"Mixed Forest",38.8929214477539,-78.1395034790039],
      ["Smithsonian Conservation Biology Institute","SCBI_033",361,"Mixed Forest",38.8929214477539,-78.1395034790039],
      ["Smithsonian Conservation Biology Institute","SCBI_011",361,"Mixed Forest",38.8929214477539,-78.1395034790039],
      ["Smithsonian Conservation Biology Institute","SCBI_018",361,"Mixed Forest",38.8929214477539,-78.1395034790039],
      ["Smithsonian Conservation Biology Institute","SCBI_007",361,"Mixed Forest",38.8929214477539,-78.1395034790039],
      ["Smithsonian Conservation Biology Institute","SCBI_017",361,"Mixed Forest",38.8929214477539,-78.1395034790039],
      ["Smithsonian Conservation Biology Institute","SCBI_006",361,"Mixed Forest",38.8929214477539,-78.1395034790039],
      ["Smithsonian Conservation Biology Institute","SCBI_049",361,"Mixed Forest",38.8929214477539,-78.1395034790039],
      ["Smithsonian Conservation Biology Institute","SCBI_038",361,"Mixed Forest",38.8929214477539,-78.1395034790039],
      ["Smithsonian Conservation Biology Institute","SCBI_016",361,"Mixed Forest",38.8929214477539,-78.1395034790039],
      ["Smithsonian Conservation Biology Institute","SCBI_005",361,"Mixed Forest",38.8929214477539,-78.1395034790039],
      ["Smithsonian Conservation Biology Institute","SCBI_015",361,"Mixed Forest",38.8929214477539,-78.1395034790039],
      ["Smithsonian Conservation Biology Institute","SCBI_004",361,"Mixed Forest",38.8929214477539,-78.1395034790039],
      ["Disney Wilderness Preserve","DSNY_061",15,"Open Shrublands",28.1250400543213,-81.43625],
      ["Disney Wilderness Preserve","DSNY_053",15,"Open Shrublands",28.1250400543213,-81.43625],
      ["Disney Wilderness Preserve","DSNY_066",15,"Open Shrublands",28.1250400543213,-81.43625],
      ["Disney Wilderness Preserve","DSNY_055",15,"Open Shrublands",28.1250400543213,-81.43625],
      ["Disney Wilderness Preserve","DSNY_011",15,"Open Shrublands",28.1250400543213,-81.43625],
      ["Disney Wilderness Preserve","DSNY_021",15,"Open Shrublands",28.1250400543213,-81.43625],
      ["Disney Wilderness Preserve","DSNY_010",15,"Open Shrublands",28.1250400543213,-81.43625],
      ["Disney Wilderness Preserve","DSNY_013",15,"Open Shrublands",28.1250400543213,-81.43625],
      ["Disney Wilderness Preserve","DSNY_002",15,"Open Shrublands",28.1250400543213,-81.43625],
      ["Disney Wilderness Preserve","DSNY_034",15,"Open Shrublands",28.1250400543213,-81.43625],
      ["Disney Wilderness Preserve","DSNY_012",15,"Open Shrublands",28.1250400543213,-81.43625],
      ["Disney Wilderness Preserve","DSNY_001",15,"Open Shrublands",28.1250400543213,-81.43625],
      ["Disney Wilderness Preserve","DSNY_015",15,"Open Shrublands",28.1250400543213,-81.43625],
      ["Disney Wilderness Preserve","DSNY_004",15,"Open Shrublands",28.1250400543213,-81.43625],
      ["Disney Wilderness Preserve","DSNY_025",15,"Open Shrublands",28.1250400543213,-81.43625],
      ["Disney Wilderness Preserve","DSNY_014",15,"Open Shrublands",28.1250400543213,-81.43625],
      ["Disney Wilderness Preserve","DSNY_003",15,"Open Shrublands",28.1250400543213,-81.43625],
      ["Disney Wilderness Preserve","DSNY_017",15,"Open Shrublands",28.1250400543213,-81.43625],
      ["Disney Wilderness Preserve","DSNY_006",15,"Open Shrublands",28.1250400543213,-81.43625],
      ["Disney Wilderness Preserve","DSNY_016",15,"Open Shrublands",28.1250400543213,-81.43625],
      ["Disney Wilderness Preserve","DSNY_005",15,"Open Shrublands",28.1250400543213,-81.43625],
      ["Disney Wilderness Preserve","DSNY_008",15,"Open Shrublands",28.1250400543213,-81.43625],
      ["Disney Wilderness Preserve","DSNY_007",15,"Open Shrublands",28.1250400543213,-81.43625],
      ["Disney Wilderness Preserve","DSNY_009",15,"Open Shrublands",28.1250400543213,-81.43625],
      ["Sabres","Smos11",81,"Croplands",44.1475,-0.8456],
      ["Hyltemossa","SE-Htm_CP04",41,"Evergreen Needleleaf Forest",56.09763,13.41897],
      ["Hyltemossa","SE-Htm_CP03",41,"Evergreen Needleleaf Forest",56.09763,13.41897],
      ["Hyltemossa","SE-Htm_CP02",41,"Evergreen Needleleaf Forest",56.09763,13.41897],
      ["Hyltemossa","SE-Htm_SP11",41,"Evergreen Needleleaf Forest",56.09763,13.41897],
      ["Hyltemossa","SE-Htm_SP12",41,"Evergreen Needleleaf Forest",56.09763,13.41897],
      ["Hyltemossa","SE-Htm_SP01",41,"Evergreen Needleleaf Forest",56.09763,13.41897],
      ["Hyltemossa","SE-Htm_SP20",41,"Evergreen Needleleaf Forest",56.09763,13.41897],
      ["Hyltemossa","SE-Htm_SP10",41,"Evergreen Needleleaf Forest",56.09763,13.41897],
      ["Hyltemossa","SE-Htm_SP15",41,"Evergreen Needleleaf Forest",56.09763,13.41897],
      ["Hyltemossa","SE-Htm_SP04",41,"Evergreen Needleleaf Forest",56.09763,13.41897],
      ["Hyltemossa","SE-Htm_SP16",41,"Evergreen Needleleaf Forest",56.09763,13.41897],
      ["Hyltemossa","SE-Htm_SP05",41,"Evergreen Needleleaf Forest",56.09763,13.41897],
      ["Hyltemossa","SE-Htm_SP13",41,"Evergreen Needleleaf Forest",56.09763,13.41897],
      ["Hyltemossa","SE-Htm_SP02",41,"Evergreen Needleleaf Forest",56.09763,13.41897],
      ["Hyltemossa","SE-Htm_SP14",41,"Evergreen Needleleaf Forest",56.09763,13.41897],
      ["Hyltemossa","SE-Htm_SP03",41,"Evergreen Needleleaf Forest",56.09763,13.41897],
      ["Hyltemossa","SE-Htm_SP19",41,"Evergreen Needleleaf Forest",56.09763,13.41897],
      ["Hyltemossa","SE-Htm_SP08",41,"Evergreen Needleleaf Forest",56.09763,13.41897],
      ["Hyltemossa","SE-Htm_CP01",41,"Evergreen Needleleaf Forest",56.09763,13.41897],
      ["Hyltemossa","SE-Htm_SP09",41,"Evergreen Needleleaf Forest",56.09763,13.41897],
      ["Hyltemossa","SE-Htm_SP17",41,"Evergreen Needleleaf Forest",56.09763,13.41897],
      ["Hyltemossa","SE-Htm_SP06",41,"Evergreen Needleleaf Forest",56.09763,13.41897],
      ["Hyltemossa","SE-Htm_SP18",41,"Evergreen Needleleaf Forest",56.09763,13.41897],
      ["Hyltemossa","SE-Htm_SP07",41,"Evergreen Needleleaf Forest",56.09763,13.41897],
      ["Warra Tall Eucalypt","WarraTallEucalypt",714,"Evergreen Broadleaf",-43.09499844,146.6544986],
      ["Santa Rita","SRER_009",983,"Closed Shrublands",31.91068,-110.83549],
      ["Santa Rita","SRER_018",983,"Closed Shrublands",31.91068,-110.83549],
      ["Santa Rita","SRER_007",983,"Closed Shrublands",31.91068,-110.83549],
      ["Santa Rita","SRER_019",983,"Closed Shrublands",31.91068,-110.83549],
      ["Santa Rita","SRER_008",983,"Closed Shrublands",31.91068,-110.83549],
      ["Santa Rita","SRER_016",983,"Closed Shrublands",31.91068,-110.83549],
      ["Santa Rita","SRER_005",983,"Closed Shrublands",31.91068,-110.83549],
      ["Santa Rita","SRER_017",983,"Closed Shrublands",31.91068,-110.83549],
      ["Santa Rita","SRER_006",983,"Closed Shrublands",31.91068,-110.83549],
      ["Santa Rita","SRER_014",983,"Closed Shrublands",31.91068,-110.83549],
      ["Santa Rita","SRER_003",983,"Closed Shrublands",31.91068,-110.83549],
      ["Santa Rita","SRER_048",983,"Closed Shrublands",31.91068,-110.83549],
      ["Santa Rita","SRER_015",983,"Closed Shrublands",31.91068,-110.83549],
      ["Santa Rita","SRER_004",983,"Closed Shrublands",31.91068,-110.83549],
      ["Santa Rita","SRER_012",983,"Closed Shrublands",31.91068,-110.83549],
      ["Santa Rita","SRER_001",983,"Closed Shrublands",31.91068,-110.83549],
      ["Santa Rita","SRER_057",983,"Closed Shrublands",31.91068,-110.83549],
      ["Santa Rita","SRER_046",983,"Closed Shrublands",31.91068,-110.83549],
      ["Santa Rita","SRER_013",983,"Closed Shrublands",31.91068,-110.83549],
      ["Santa Rita","SRER_002",983,"Closed Shrublands",31.91068,-110.83549],
      ["Santa Rita","SRER_010",983,"Closed Shrublands",31.91068,-110.83549],
      ["Santa Rita","SRER_011",983,"Closed Shrublands",31.91068,-110.83549],
      ["Santa Rita","SRER_020",983,"Closed Shrublands",31.91068,-110.83549],
      ["Brasschaat","BE-Bra_CP04",16,"Mixed Forest",51.3075,4.5199],
      ["Brasschaat","BE-Bra_CP03",16,"Mixed Forest",51.3075,4.5199],
      ["Brasschaat","Brasschaat",16,"Mixed Forest",51.3075,4.5199],
      ["Brasschaat","BE-Bra_CP02",16,"Mixed Forest",51.3075,4.5199],
      ["Brasschaat","BE-Bra_CP01",16,"Mixed Forest",51.3075,4.5199],
      ["Montaut","Smos6",295,"Croplands",43.1922,1.6436],
      ["Calperum","Calperum",53,"Closed Shrublands",-34.0027008056641,140.587707519531],
      ["Sioux Falls Uscrn","s1",497,"Croplands",43.73456,-96.62197],
      ["Tereno","te2",610,"Deciduous Broadleaf",50.5049018859863,6.33109],
      ["Tereno","te1",610,"Deciduous Broadleaf",50.5049018859863,6.33109],
      ["Tereno","te4",610,"Deciduous Broadleaf",50.5049018859863,6.33109],
      ["Tereno","te3",610,"Deciduous Broadleaf",50.5049018859863,6.33109],
      ["Tereno","te5",610,"Deciduous Broadleaf",50.5049018859863,6.33109],
      ["Des Moines","Des_Moines",281,"Croplands",41.5563,-93.2854995727539],
      ["Narbonne","Smos8",112,"Evergreen Needleleaf Forest",43.15,2.9567],
      ["Barnas","Smos1",480,"Evergreen Needleleaf Forest",44.666,4.15983],
      ["Batesville","WNW",136,"Grassland",35.82,-91.78],
      ["Peyrusse Grande","Smos9",245,"Croplands",43.6664,0.2217],
      ["Tryon","E35",294,"Grassland",35.8615,-97.0695],
      ["San Rossore 2","IT-SR2_SP12",1,"Evergreen Needleleaf Forest",43.73202,10.29091],
      ["San Rossore 2","IT-SR2_SP01",1,"Evergreen Needleleaf Forest",43.73202,10.29091],
      ["San Rossore 2","IT-SR2_SP13",1,"Evergreen Needleleaf Forest",43.73202,10.29091],
      ["San Rossore 2","IT-SR2_SP02",1,"Evergreen Needleleaf Forest",43.73202,10.29091],
      ["San Rossore 2","IT-SR2_SP14",1,"Evergreen Needleleaf Forest",43.73202,10.29091],
      ["San Rossore 2","IT-SR2_SP03",1,"Evergreen Needleleaf Forest",43.73202,10.29091],
      ["San Rossore 2","IT-SR2_SP15",1,"Evergreen Needleleaf Forest",43.73202,10.29091],
      ["San Rossore 2","IT-SR2_SP04",1,"Evergreen Needleleaf Forest",43.73202,10.29091],
      ["San Rossore 2","IT-SR2_SP20",1,"Evergreen Needleleaf Forest",43.73202,10.29091],
      ["San Rossore 2","IT-SR2_SP10",1,"Evergreen Needleleaf Forest",43.73202,10.29091],
      ["San Rossore 2","IT-SR2_SP11",1,"Evergreen Needleleaf Forest",43.73202,10.29091],
      ["San Rossore 2","IT-SR2_SP09",1,"Evergreen Needleleaf Forest",43.73202,10.29091],
      ["San Rossore 2","IT-SR2_CP01",1,"Evergreen Needleleaf Forest",43.73202,10.29091],
      ["San Rossore 2","IT-SR2_CP02",1,"Evergreen Needleleaf Forest",43.73202,10.29091],
      ["San Rossore 2","IT-SR2_SP16",1,"Evergreen Needleleaf Forest",43.73202,10.29091],
      ["San Rossore 2","IT-SR2_SP05",1,"Evergreen Needleleaf Forest",43.73202,10.29091],
      ["San Rossore 2","IT-SR2_SP17",1,"Evergreen Needleleaf Forest",43.73202,10.29091],
      ["San Rossore 2","IT-SR2_SP06",1,"Evergreen Needleleaf Forest",43.73202,10.29091],
      ["San Rossore 2","IT-SR2_SP18",1,"Evergreen Needleleaf Forest",43.73202,10.29091],
      ["San Rossore 2","IT-SR2_SP07",1,"Evergreen Needleleaf Forest",43.73202,10.29091],
      ["San Rossore 2","IT-SR2_SP08",1,"Evergreen Needleleaf Forest",43.73202,10.29091],
      ["Siikaneva","Siikaneva",160,"Permanent Wetland",61.83265,24.19285],
      ["Imnavait Creek","i1",929,"Tundra",68.61654,-149.3032],
      ["Central Plains Experimental Range","CPER_015",1648,"Grasslands",40.81555,-104.74566],
      ["Central Plains Experimental Range","CPER_004",1648,"Grasslands",40.81555,-104.74566],
      ["Central Plains Experimental Range","CPER_014",1648,"Grasslands",40.81555,-104.74566],
      ["Central Plains Experimental Range","CPER_003",1648,"Grasslands",40.81555,-104.74566],
      ["Central Plains Experimental Range","CPER_046",1648,"Grasslands",40.81555,-104.74566],
      ["Central Plains Experimental Range","CPER_013",1648,"Grasslands",40.81555,-104.74566],
      ["Central Plains Experimental Range","CPER_002",1648,"Grasslands",40.81555,-104.74566],
      ["Central Plains Experimental Range","CPER_056",1648,"Grasslands",40.81555,-104.74566],
      ["Central Plains Experimental Range","CPER_012",1648,"Grasslands",40.81555,-104.74566],
      ["Central Plains Experimental Range","CPER_001",1648,"Grasslands",40.81555,-104.74566],
      ["Central Plains Experimental Range","CPER_011",1648,"Grasslands",40.81555,-104.74566],
      ["Central Plains Experimental Range","CPER_010",1648,"Grasslands",40.81555,-104.74566],
      ["Central Plains Experimental Range","CPER_020",1648,"Grasslands",40.81555,-104.74566],
      ["Central Plains Experimental Range","CPER_062",1648,"Grasslands",40.81555,-104.74566],
      ["Central Plains Experimental Range","CPER_009",1648,"Grasslands",40.81555,-104.74566],
      ["Central Plains Experimental Range","CPER_019",1648,"Grasslands",40.81555,-104.74566],
      ["Central Plains Experimental Range","CPER_008",1648,"Grasslands",40.81555,-104.74566],
      ["Central Plains Experimental Range","CPER_018",1648,"Grasslands",40.81555,-104.74566],
      ["Central Plains Experimental Range","CPER_007",1648,"Grasslands",40.81555,-104.74566],
      ["Central Plains Experimental Range","CPER_017",1648,"Grasslands",40.81555,-104.74566],
      ["Central Plains Experimental Range","CPER_006",1648,"Grasslands",40.81555,-104.74566],
      ["Central Plains Experimental Range","CPER_016",1648,"Grasslands",40.81555,-104.74566],
      ["Central Plains Experimental Range","CPER_005",1648,"Grasslands",40.81555,-104.74566],
      ["Lenoir Landing","LENO_014",13,"Deciduous Broadleaf Forest",31.853861,-88.161181],
      ["Lenoir Landing","LENO_003",13,"Deciduous Broadleaf Forest",31.853861,-88.161181],
      ["Lenoir Landing","LENO_015",13,"Deciduous Broadleaf Forest",31.853861,-88.161181],
      ["Lenoir Landing","LENO_004",13,"Deciduous Broadleaf Forest",31.853861,-88.161181],
      ["Lenoir Landing","LENO_067",13,"Deciduous Broadleaf Forest",31.853861,-88.161181],
      ["Lenoir Landing","LENO_012",13,"Deciduous Broadleaf Forest",31.853861,-88.161181],
      ["Lenoir Landing","LENO_001",13,"Deciduous Broadleaf Forest",31.853861,-88.161181],
      ["Lenoir Landing","LENO_013",13,"Deciduous Broadleaf Forest",31.853861,-88.161181],
      ["Lenoir Landing","LENO_002",13,"Deciduous Broadleaf Forest",31.853861,-88.161181],
      ["Lenoir Landing","LENO_021",13,"Deciduous Broadleaf Forest",31.853861,-88.161181],
      ["Lenoir Landing","LENO_010",13,"Deciduous Broadleaf Forest",31.853861,-88.161181],
      ["Lenoir Landing","LENO_022",13,"Deciduous Broadleaf Forest",31.853861,-88.161181],
      ["Lenoir Landing","LENO_011",13,"Deciduous Broadleaf Forest",31.853861,-88.161181],
      ["Lenoir Landing","LENO_063",13,"Deciduous Broadleaf Forest",31.853861,-88.161181],
      ["Lenoir Landing","LENO_064",13,"Deciduous Broadleaf Forest",31.853861,-88.161181],
      ["Lenoir Landing","LENO_009",13,"Deciduous Broadleaf Forest",31.853861,-88.161181],
      ["Lenoir Landing","LENO_018",13,"Deciduous Broadleaf Forest",31.853861,-88.161181],
      ["Lenoir Landing","LENO_007",13,"Deciduous Broadleaf Forest",31.853861,-88.161181],
      ["Lenoir Landing","LENO_008",13,"Deciduous Broadleaf Forest",31.853861,-88.161181],
      ["Lenoir Landing","LENO_016",13,"Deciduous Broadleaf Forest",31.853861,-88.161181],
      ["Lenoir Landing","LENO_005",13,"Deciduous Broadleaf Forest",31.853861,-88.161181],
      ["Lenoir Landing","LENO_017",13,"Deciduous Broadleaf Forest",31.853861,-88.161181],
      ["Lenoir Landing","LENO_006",13,"Deciduous Broadleaf Forest",31.853861,-88.161181],
      ["Robson Creek Rainforest","RobsonCreekRainforest",680,"Mixed Forest",-17.117469,145.630139],
      ["Lyndon B. Johnson National Grassland","CLBJ_002",272,"Deciduous Broadleaf Forest",33.40123,-97.57],
      ["Lyndon B. Johnson National Grassland","CLBJ_003",272,"Deciduous Broadleaf Forest",33.40123,-97.57],
      ["Lyndon B. Johnson National Grassland","CLBJ_001",272,"Deciduous Broadleaf Forest",33.40123,-97.57],
      ["AQUI Parc Meteo","AQ1",108,"Croplands Mosaics",44.79,0.58],
      ["Duke Forest","DukeForest",170,"Mixed Forest",35.9712,-79.0934],
      ["Tibetian Plateau (Ngari)","NGARI2",4712,"Grasslands",31.33,91.854],
      ["Tibetian Plateau (Ngari)","NGARI1",4712,"Grasslands",31.33,91.854],
      ["Dry River","DryRiver",175,"Woody Savannas",-15.259,132.371],
      ["Gingin","Gingin",111,"Woody Savannas",-31.3764,115.7139],
      ["Tucson","W",164,"Open Shrublands",32.24,-111.17],
      ["Goodwin Creek","Goodwin_Creek_MS",98,"Deciduous Broadleaf",34.25505,-89.8736],
      ["Pu u Maka ala Natural Area Reserve","PUUM_039",1685,"Evergreen Broadleaf",19.55309,-155.31731],
      ["Pu u Maka ala Natural Area Reserve","PUUM_031",1685,"Evergreen Broadleaf",19.55309,-155.31731],
      ["Pu u Maka ala Natural Area Reserve","PUUM_041",1685,"Evergreen Broadleaf",19.55309,-155.31731],
      ["Barlad","Br1",172,"Croplands",46.23313,27.64438],
      ["Tibetian Plateau (Maqu)","MAQU",3725,"Croplands",33.68,101.89],
      ["Hainich","ha1",430,"Mixed Forest",51.0792007446289,10.4522],
      ["Hainich","ha4",430,"Mixed Forest",51.0792007446289,10.4522],
      ["Hainich","ha6",430,"Mixed Forest",51.0792007446289,10.4522],
      ["Hainich","ha5",430,"Mixed Forest",51.0792007446289,10.4522],
      ["Tumbarumba","tu1",1200,"Evergreen Broadleaf",-35.65652,148.15163],
      ["Ordway Swisher Biological Station","OSBS_009",45,"Evergreen Needleleaf",29.6839,-81.9934],
      ["Ordway Swisher Biological Station","OSBS_008",45,"Evergreen Needleleaf",29.6839,-81.9934],
      ["Ordway Swisher Biological Station","OSBS_007",45,"Evergreen Needleleaf",29.6839,-81.9934],
      ["Ordway Swisher Biological Station","OSBS_006",45,"Evergreen Needleleaf",29.6839,-81.9934],
      ["Ordway Swisher Biological Station","OSBS_038",45,"Evergreen Needleleaf",29.6839,-81.9934],
      ["Ordway Swisher Biological Station","OSBS_016",45,"Evergreen Needleleaf",29.6839,-81.9934],
      ["Ordway Swisher Biological Station","OSBS_005",45,"Evergreen Needleleaf",29.6839,-81.9934],
      ["Ordway Swisher Biological Station","OSBS_048",45,"Evergreen Needleleaf",29.6839,-81.9934],
      ["Ordway Swisher Biological Station","OSBS_015",45,"Evergreen Needleleaf",29.6839,-81.9934],
      ["Ordway Swisher Biological Station","OSBS_004",45,"Evergreen Needleleaf",29.6839,-81.9934],
      ["Ordway Swisher Biological Station","OSBS_025",45,"Evergreen Needleleaf",29.6839,-81.9934],
      ["Ordway Swisher Biological Station","OSBS_003",45,"Evergreen Needleleaf",29.6839,-81.9934],
      ["Ordway Swisher Biological Station","OSBS_024",45,"Evergreen Needleleaf",29.6839,-81.9934],
      ["Ordway Swisher Biological Station","OSBS_002",45,"Evergreen Needleleaf",29.6839,-81.9934],
      ["Ordway Swisher Biological Station","OSBS_023",45,"Evergreen Needleleaf",29.6839,-81.9934],
      ["Ordway Swisher Biological Station","OSBS_012",45,"Evergreen Needleleaf",29.6839,-81.9934],
      ["Ordway Swisher Biological Station","OSBS_001",45,"Evergreen Needleleaf",29.6839,-81.9934],
      ["Ordway Swisher Biological Station","OSBS_022",45,"Evergreen Needleleaf",29.6839,-81.9934],
      ["Ordway Swisher Biological Station","OSBS_011",45,"Evergreen Needleleaf",29.6839,-81.9934],
      ["Ordway Swisher Biological Station","OSBS_010",45,"Evergreen Needleleaf",29.6839,-81.9934],
      ["Ordway Swisher Biological Station","OSBS_030",45,"Evergreen Needleleaf",29.6839,-81.9934],
      ["Ordway Swisher Biological Station","OSBS_051",45,"Evergreen Needleleaf",29.6839,-81.9934],
      ["Konza Prairie Biological Station","KONA_073",323,"Croplands",39.110446,-96.612935],
      ["Konza Prairie Biological Station","KONA_074",323,"Croplands",39.110446,-96.612935],
      ["Konza Prairie Biological Station","KONA_071",323,"Croplands",39.110446,-96.612935],
      ["Konza Prairie Biological Station","KONA_070",323,"Croplands",39.110446,-96.612935],
      ["Guanica Forest","GUAN_003",143,"Evergreen Broadleaf",17.9695491790771,-66.8686981201172],
      ["Guanica Forest","GUAN_013",143,"Evergreen Broadleaf",17.9695491790771,-66.8686981201172],
      ["Guanica Forest","GUAN_002",143,"Evergreen Broadleaf",17.9695491790771,-66.8686981201172],
      ["Guanica Forest","GUAN_012",143,"Evergreen Broadleaf",17.9695491790771,-66.8686981201172],
      ["Guanica Forest","GUAN_001",143,"Evergreen Broadleaf",17.9695491790771,-66.8686981201172],
      ["Guanica Forest","GUAN_055",143,"Evergreen Broadleaf",17.9695491790771,-66.8686981201172],
      ["Guanica Forest","GUAN_011",143,"Evergreen Broadleaf",17.9695491790771,-66.8686981201172],
      ["Guanica Forest","GUAN_054",143,"Evergreen Broadleaf",17.9695491790771,-66.8686981201172],
      ["Guanica Forest","GUAN_010",143,"Evergreen Broadleaf",17.9695491790771,-66.8686981201172],
      ["Guanica Forest","GUAN_020",143,"Evergreen Broadleaf",17.9695491790771,-66.8686981201172],
      ["Guanica Forest","GUAN_052",143,"Evergreen Broadleaf",17.9695491790771,-66.8686981201172],
      ["Guanica Forest","GUAN_009",143,"Evergreen Broadleaf",17.9695491790771,-66.8686981201172],
      ["Guanica Forest","GUAN_019",143,"Evergreen Broadleaf",17.9695491790771,-66.8686981201172],
      ["Guanica Forest","GUAN_008",143,"Evergreen Broadleaf",17.9695491790771,-66.8686981201172],
      ["Guanica Forest","GUAN_018",143,"Evergreen Broadleaf",17.9695491790771,-66.8686981201172],
      ["Guanica Forest","GUAN_007",143,"Evergreen Broadleaf",17.9695491790771,-66.8686981201172],
      ["Guanica Forest","GUAN_017",143,"Evergreen Broadleaf",17.9695491790771,-66.8686981201172],
      ["Guanica Forest","GUAN_006",143,"Evergreen Broadleaf",17.9695491790771,-66.8686981201172],
      ["Guanica Forest","GUAN_016",143,"Evergreen Broadleaf",17.9695491790771,-66.8686981201172],
      ["Guanica Forest","GUAN_005",143,"Evergreen Broadleaf",17.9695491790771,-66.8686981201172],
      ["Guanica Forest","GUAN_015",143,"Evergreen Broadleaf",17.9695491790771,-66.8686981201172],
      ["Guanica Forest","GUAN_004",143,"Evergreen Broadleaf",17.9695491790771,-66.8686981201172],
      ["University of Kansas Field Site","UKFS_015",322,"Deciduous Broadleaf Forest",39.040431,-95.19215],
      ["University of Kansas Field Site","UKFS_004",322,"Deciduous Broadleaf Forest",39.040431,-95.19215],
      ["University of Kansas Field Site","UKFS_016",322,"Deciduous Broadleaf Forest",39.040431,-95.19215],
      ["University of Kansas Field Site","UKFS_005",322,"Deciduous Broadleaf Forest",39.040431,-95.19215],
      ["University of Kansas Field Site","UKFS_017",322,"Deciduous Broadleaf Forest",39.040431,-95.19215],
      ["University of Kansas Field Site","UKFS_006",322,"Deciduous Broadleaf Forest",39.040431,-95.19215],
      ["University of Kansas Field Site","UKFS_018",322,"Deciduous Broadleaf Forest",39.040431,-95.19215],
      ["University of Kansas Field Site","UKFS_007",322,"Deciduous Broadleaf Forest",39.040431,-95.19215],
      ["University of Kansas Field Site","UKFS_019",322,"Deciduous Broadleaf Forest",39.040431,-95.19215],
      ["University of Kansas Field Site","UKFS_008",322,"Deciduous Broadleaf Forest",39.040431,-95.19215],
      ["University of Kansas Field Site","UKFS_009",322,"Deciduous Broadleaf Forest",39.040431,-95.19215],
      ["University of Kansas Field Site","UKFS_053",322,"Deciduous Broadleaf Forest",39.040431,-95.19215],
      ["University of Kansas Field Site","UKFS_010",322,"Deciduous Broadleaf Forest",39.040431,-95.19215],
      ["University of Kansas Field Site","UKFS_011",322,"Deciduous Broadleaf Forest",39.040431,-95.19215],
      ["University of Kansas Field Site","UKFS_012",322,"Deciduous Broadleaf Forest",39.040431,-95.19215],
      ["University of Kansas Field Site","UKFS_001",322,"Deciduous Broadleaf Forest",39.040431,-95.19215],
      ["University of Kansas Field Site","UKFS_013",322,"Deciduous Broadleaf Forest",39.040431,-95.19215],
      ["University of Kansas Field Site","UKFS_002",322,"Deciduous Broadleaf Forest",39.040431,-95.19215],
      ["University of Kansas Field Site","UKFS_058",322,"Deciduous Broadleaf Forest",39.040431,-95.19215],
      ["University of Kansas Field Site","UKFS_047",322,"Deciduous Broadleaf Forest",39.040431,-95.19215],
      ["University of Kansas Field Site","UKFS_025",322,"Deciduous Broadleaf Forest",39.040431,-95.19215],
      ["University of Kansas Field Site","UKFS_014",322,"Deciduous Broadleaf Forest",39.040431,-95.19215],
      ["University of Kansas Field Site","UKFS_003",322,"Deciduous Broadleaf Forest",39.040431,-95.19215],
      ["Vielsalm","BE-Vie_SP14",483,"Mixed Forest",50.304962,5.998099],
      ["Vielsalm","BE-Vie_SP03",483,"Mixed Forest",50.304962,5.998099],
      ["Vielsalm","BE-Vie_SP13",483,"Mixed Forest",50.304962,5.998099],
      ["Vielsalm","BE-Vie_SP02",483,"Mixed Forest",50.304962,5.998099],
      ["Vielsalm","BE-Vie_SP12",483,"Mixed Forest",50.304962,5.998099],
      ["Vielsalm","BE-Vie_SP01",483,"Mixed Forest",50.304962,5.998099],
      ["Vielsalm","BE-Vie_SP11",483,"Mixed Forest",50.304962,5.998099],
      ["Vielsalm","BE-Vie_SP10",483,"Mixed Forest",50.304962,5.998099],
      ["Vielsalm","BE-Vie_SP20",483,"Mixed Forest",50.304962,5.998099],
      ["Vielsalm","BE-Vie_SP09",483,"Mixed Forest",50.304962,5.998099],
      ["Vielsalm","BE-Vie_SP19",483,"Mixed Forest",50.304962,5.998099],
      ["Vielsalm","BE-Vie_SP08",483,"Mixed Forest",50.304962,5.998099],
      ["Vielsalm","BE-Vie_SP18",483,"Mixed Forest",50.304962,5.998099],
      ["Vielsalm","BE-Vie_SP07",483,"Mixed Forest",50.304962,5.998099],
      ["Vielsalm","BE-Vie_SP17",483,"Mixed Forest",50.304962,5.998099],
      ["Vielsalm","BE-Vie_SP06",483,"Mixed Forest",50.304962,5.998099],
      ["Vielsalm","BE-Vie_SP16",483,"Mixed Forest",50.304962,5.998099],
      ["Vielsalm","BE-Vie_SP05",483,"Mixed Forest",50.304962,5.998099],
      ["Vielsalm","BE-Vie_SP15",483,"Mixed Forest",50.304962,5.998099],
      ["Vielsalm","BE-Vie_SP04",483,"Mixed Forest",50.304962,5.998099],
      ["Vielsalm","BE-Vie_CP01",483,"Mixed Forest",50.304962,5.998099],
      ["Vielsalm","BE-Vie_CP02",483,"Mixed Forest",50.304962,5.998099],
      ["Oak Ridge","ORNL_031",334,"Mixed Forest",35.9641189575195,-84.282600402832],
      ["Oak Ridge","ORNL_054",334,"Mixed Forest",35.9641189575195,-84.282600402832],
      ["Oak Ridge","ORNL_032",334,"Mixed Forest",35.9641189575195,-84.282600402832],
      ["Oak Ridge","ORNL_021",334,"Mixed Forest",35.9641189575195,-84.282600402832],
      ["Oak Ridge","ORNL_010",334,"Mixed Forest",35.9641189575195,-84.282600402832],
      ["Oak Ridge","ORNL_066",334,"Mixed Forest",35.9641189575195,-84.282600402832],
      ["Oak Ridge","ORNL_044",334,"Mixed Forest",35.9641189575195,-84.282600402832],
      ["Oak Ridge","ORNL_033",334,"Mixed Forest",35.9641189575195,-84.282600402832],
      ["Oak Ridge","ORNL_045",334,"Mixed Forest",35.9641189575195,-84.282600402832],
      ["Oak Ridge","ORNL_012",334,"Mixed Forest",35.9641189575195,-84.282600402832],
      ["Oak Ridge","ORNL_001",334,"Mixed Forest",35.9641189575195,-84.282600402832],
      ["Oak Ridge","ORNL_035",334,"Mixed Forest",35.9641189575195,-84.282600402832],
      ["Oak Ridge","ORNL_002",334,"Mixed Forest",35.9641189575195,-84.282600402832],
      ["Oak Ridge","ORNL_014",334,"Mixed Forest",35.9641189575195,-84.282600402832],
      ["Oak Ridge","ORNL_003",334,"Mixed Forest",35.9641189575195,-84.282600402832],
      ["Oak Ridge","ORNL_004",334,"Mixed Forest",35.9641189575195,-84.282600402832],
      ["Oak Ridge","ORNL_027",334,"Mixed Forest",35.9641189575195,-84.282600402832],
      ["Oak Ridge","ORNL_006",334,"Mixed Forest",35.9641189575195,-84.282600402832],
      ["Oak Ridge","ORNL_029",334,"Mixed Forest",35.9641189575195,-84.282600402832],
      ["Oak Ridge","ORNL_007",334,"Mixed Forest",35.9641189575195,-84.282600402832],
      ["Oak Ridge","ORNL_008",334,"Mixed Forest",35.9641189575195,-84.282600402832],
      ["Oak Ridge","ORNL_009",334,"Mixed Forest",35.9641189575195,-84.282600402832],
      ["Oak Ridge","ORNL_050",334,"Mixed Forest",35.9641189575195,-84.282600402832],
      ["Inner Mongolia","IM1",1426,"Grasslands",45.74,106.26],
      ["Alice Mulga","AliceMulga",583,"Open Shrublands",-22.283236,133.251096],
      ["Hyytiala","FI-Hyy_SP17",181,"Evergreen Needleleaf",61.8474006652832,24.2947998046875],
      ["Hyytiala","FI-Hyy_SP18",181,"Evergreen Needleleaf",61.8474006652832,24.2947998046875],
      ["Hyytiala","FI-Hyy_SP19",181,"Evergreen Needleleaf",61.8474006652832,24.2947998046875],
      ["Hyytiala","FI-Hyy_SP13",181,"Evergreen Needleleaf",61.8474006652832,24.2947998046875],
      ["Hyytiala","FI-Hyy_SP14",181,"Evergreen Needleleaf",61.8474006652832,24.2947998046875],
      ["Hyytiala","FI-Hyy_SP15",181,"Evergreen Needleleaf",61.8474006652832,24.2947998046875],
      ["Hyytiala","FI-Hyy_SP16",181,"Evergreen Needleleaf",61.8474006652832,24.2947998046875],
      ["Hyytiala","h1",181,"Evergreen Needleleaf",61.8474006652832,24.2947998046875],
      ["Hyytiala","FI-Hyy_CP03",181,"Evergreen Needleleaf",61.8474006652832,24.2947998046875],
      ["Hyytiala","FI-Hyy_CP02",181,"Evergreen Needleleaf",61.8474006652832,24.2947998046875],
      ["Hyytiala","FI-Hyy_CP04",181,"Evergreen Needleleaf",61.8474006652832,24.2947998046875],
      ["Hyytiala","FI-Hyy_CP01",181,"Evergreen Needleleaf",61.8474006652832,24.2947998046875],
      ["Hyytiala","FI-Hyy_SP20",181,"Evergreen Needleleaf",61.8474006652832,24.2947998046875],
      ["Hyytiala","FI-Hyy_SP01",181,"Evergreen Needleleaf",61.8474006652832,24.2947998046875],
      ["Hyytiala","FI-Hyy_SP06",181,"Evergreen Needleleaf",61.8474006652832,24.2947998046875],
      ["Hyytiala","FI-Hyy_SP07",181,"Evergreen Needleleaf",61.8474006652832,24.2947998046875],
      ["Hyytiala","FI-Hyy_SP08",181,"Evergreen Needleleaf",61.8474006652832,24.2947998046875],
      ["Hyytiala","FI-Hyy_SP09",181,"Evergreen Needleleaf",61.8474006652832,24.2947998046875],
      ["Hyytiala","FI-Hyy_SP02",181,"Evergreen Needleleaf",61.8474006652832,24.2947998046875],
      ["Hyytiala","FI-Hyy_SP03",181,"Evergreen Needleleaf",61.8474006652832,24.2947998046875],
      ["Hyytiala","FI-Hyy_SP04",181,"Evergreen Needleleaf",61.8474006652832,24.2947998046875],
      ["Hyytiala","FI-Hyy_SP05",181,"Evergreen Needleleaf",61.8474006652832,24.2947998046875],
      ["Hyytiala","FI-Hyy_SP10",181,"Evergreen Needleleaf",61.8474006652832,24.2947998046875],
      ["Hyytiala","FI-Hyy_SP11",181,"Evergreen Needleleaf",61.8474006652832,24.2947998046875],
      ["Hyytiala","FI-Hyy_SP12",181,"Evergreen Needleleaf",61.8474006652832,24.2947998046875],
      ["Talladega National Forest","TALL_048",135,"Evergreen Needleleaf",32.9504585266113,-87.3932723999023],
      ["Talladega National Forest","TALL_049",135,"Evergreen Needleleaf",32.9504585266113,-87.3932723999023],
      ["Talladega National Forest","TALL_046",135,"Evergreen Needleleaf",32.9504585266113,-87.3932723999023],
      ["Walnut Gulch Kendall","w7",1531,"Grasslands",31.73643,-109.9418],
      ["Walnut Gulch Kendall","w8",1531,"Grasslands",31.73643,-109.9418],
      ["Walnut Gulch Kendall","w9",1531,"Grasslands",31.73643,-109.9418],
      ["Walnut Gulch Kendall","WalnutGulch",1531,"Grasslands",31.73643,-109.9418],
      ["Walnut Gulch Kendall","w20",1531,"Grasslands",31.73643,-109.9418],
      ["Walnut Gulch Kendall","w11",1531,"Grasslands",31.73643,-109.9418],
      ["Walnut Gulch Kendall","w21",1531,"Grasslands",31.73643,-109.9418],
      ["Walnut Gulch Kendall","w13",1531,"Grasslands",31.73643,-109.9418],
      ["Walnut Gulch Kendall","w12",1531,"Grasslands",31.73643,-109.9418],
      ["Walnut Gulch Kendall","w1",1531,"Grasslands",31.73643,-109.9418],
      ["Walnut Gulch Kendall","w15",1531,"Grasslands",31.73643,-109.9418],
      ["Walnut Gulch Kendall","w2",1531,"Grasslands",31.73643,-109.9418],
      ["Walnut Gulch Kendall","w14",1531,"Grasslands",31.73643,-109.9418],
      ["Walnut Gulch Kendall","w3",1531,"Grasslands",31.73643,-109.9418],
      ["Walnut Gulch Kendall","w17",1531,"Grasslands",31.73643,-109.9418],
      ["Walnut Gulch Kendall","w4",1531,"Grasslands",31.73643,-109.9418],
      ["Walnut Gulch Kendall","w16",1531,"Grasslands",31.73643,-109.9418],
      ["Walnut Gulch Kendall","w5",1531,"Grasslands",31.73643,-109.9418],
      ["Walnut Gulch Kendall","w19",1531,"Grasslands",31.73643,-109.9418],
      ["Walnut Gulch Kendall","w6",1531,"Grasslands",31.73643,-109.9418],
      ["Walnut Gulch Kendall","w18",1531,"Grasslands",31.73643,-109.9418],
      ["Fontainebleau-Barbeau","FR-Fon_CP04",85,"Deciduous Broadleaf Forest",48.476357,2.780096],
      ["Fontainebleau-Barbeau","FR-Fon_SP10",85,"Deciduous Broadleaf Forest",48.476357,2.780096],
      ["Fontainebleau-Barbeau","FR-Fon_SP20",85,"Deciduous Broadleaf Forest",48.476357,2.780096],
      ["Fontainebleau-Barbeau","FR-Fon_CP01",85,"Deciduous Broadleaf Forest",48.476357,2.780096],
      ["Fontainebleau-Barbeau","FR-Fon_CP02",85,"Deciduous Broadleaf Forest",48.476357,2.780096],
      ["Fontainebleau-Barbeau","FR-Fon_CP03",85,"Deciduous Broadleaf Forest",48.476357,2.780096],
      ["Fontainebleau-Barbeau","FR-Fon_SP14",85,"Deciduous Broadleaf Forest",48.476357,2.780096],
      ["Fontainebleau-Barbeau","FR-Fon_SP03",85,"Deciduous Broadleaf Forest",48.476357,2.780096],
      ["Fontainebleau-Barbeau","FR-Fon_SP13",85,"Deciduous Broadleaf Forest",48.476357,2.780096],
      ["Fontainebleau-Barbeau","FR-Fon_SP02",85,"Deciduous Broadleaf Forest",48.476357,2.780096],
      ["Fontainebleau-Barbeau","FR-Fon_SP12",85,"Deciduous Broadleaf Forest",48.476357,2.780096],
      ["Fontainebleau-Barbeau","FR-Fon_SP01",85,"Deciduous Broadleaf Forest",48.476357,2.780096],
      ["Fontainebleau-Barbeau","FR-Fon_SP11",85,"Deciduous Broadleaf Forest",48.476357,2.780096],
      ["Fontainebleau-Barbeau","FR-Fon_SP18",85,"Deciduous Broadleaf Forest",48.476357,2.780096],
      ["Fontainebleau-Barbeau","FR-Fon_SP07",85,"Deciduous Broadleaf Forest",48.476357,2.780096],
      ["Fontainebleau-Barbeau","FR-Fon_SP17",85,"Deciduous Broadleaf Forest",48.476357,2.780096],
      ["Fontainebleau-Barbeau","FR-Fon_SP06",85,"Deciduous Broadleaf Forest",48.476357,2.780096],
      ["Fontainebleau-Barbeau","FR-Fon_SP16",85,"Deciduous Broadleaf Forest",48.476357,2.780096],
      ["Fontainebleau-Barbeau","FR-Fon_SP05",85,"Deciduous Broadleaf Forest",48.476357,2.780096],
      ["Fontainebleau-Barbeau","FR-Fon_SP15",85,"Deciduous Broadleaf Forest",48.476357,2.780096],
      ["Fontainebleau-Barbeau","FR-Fon_SP04",85,"Deciduous Broadleaf Forest",48.476357,2.780096],
      ["Fontainebleau-Barbeau","FR-Fon_SP09",85,"Deciduous Broadleaf Forest",48.476357,2.780096],
      ["Fontainebleau-Barbeau","FR-Fon_SP19",85,"Deciduous Broadleaf Forest",48.476357,2.780096],
      ["Fontainebleau-Barbeau","FR-Fon_SP08",85,"Deciduous Broadleaf Forest",48.476357,2.780096],
      ["Bondville","Bondville_IL",230,"Croplands",40.0519218444824,-88.3730926513672],
      ["AQUI Fraye-Hillan","A1",49,"Croplands Mosaics",44.4734,-0.7534],
      ["AQUI Fraye-Hillan","A2",49,"Croplands Mosaics",44.4734,-0.7534],
      ["AQUI Fraye-Hillan","A3",49,"Croplands Mosaics",44.4734,-0.7534],
      ["Williams","Williams",1826,"Open Shrublands",35.75503,-112.33744],
      ["Daly Uncleared River","DalyUncleared",124,"Woody Savannas",-14.1592,131.3881],
      ["Saint Felix de Lauragais","Smos12",337,"Croplands",43.4417,1.88],
      ["Savennes","Smos13",158,"Croplands",43.825,1.1767],
      ["Mazan-Abbaye","Smos5",1240,"Grassland",44.73383,4.08383],
      ["Lajas Experimental Station","LAJA_047",24,"Grasslands",18.02125,-67.0769],
      ["Lajas Experimental Station","LAJA_065",24,"Grasslands",18.02125,-67.0769],
      ["Lajas Experimental Station","LAJA_054",24,"Grasslands",18.02125,-67.0769],
      ["Harvard Forest","HARV_008",351,"Mixed Forest",42.5377998352051,-72.171501159668],
      ["Harvard Forest","HARV_006",351,"Mixed Forest",42.5377998352051,-72.171501159668],
      ["Harvard Forest","HARV_026",351,"Mixed Forest",42.5377998352051,-72.171501159668],
      ["Harvard Forest","HARV_004",351,"Mixed Forest",42.5377998352051,-72.171501159668],
      ["Harvard Forest","HARV_049",351,"Mixed Forest",42.5377998352051,-72.171501159668],
      ["Harvard Forest","HARV_027",351,"Mixed Forest",42.5377998352051,-72.171501159668],
      ["Harvard Forest","HARV_016",351,"Mixed Forest",42.5377998352051,-72.171501159668],
      ["Harvard Forest","HARV_005",351,"Mixed Forest",42.5377998352051,-72.171501159668],
      ["Harvard Forest","HARV_013",351,"Mixed Forest",42.5377998352051,-72.171501159668],
      ["Harvard Forest","HARV_002",351,"Mixed Forest",42.5377998352051,-72.171501159668],
      ["Harvard Forest","HARV_025",351,"Mixed Forest",42.5377998352051,-72.171501159668],
      ["Harvard Forest","HARV_014",351,"Mixed Forest",42.5377998352051,-72.171501159668],
      ["Harvard Forest","HARV_022",351,"Mixed Forest",42.5377998352051,-72.171501159668],
      ["Harvard Forest","HARV_023",351,"Mixed Forest",42.5377998352051,-72.171501159668],
      ["Harvard Forest","HARV_012",351,"Mixed Forest",42.5377998352051,-72.171501159668],
      ["Harvard Forest","HARV_001",351,"Mixed Forest",42.5377998352051,-72.171501159668],
      ["Harvard Forest","HARV_020",351,"Mixed Forest",42.5377998352051,-72.171501159668],
      ["Harvard Forest","HARV_021",351,"Mixed Forest",42.5377998352051,-72.171501159668],
      ["Harvard Forest","HARV_010",351,"Mixed Forest",42.5377998352051,-72.171501159668],
      ["Harvard Forest","HARV_041",351,"Mixed Forest",42.5377998352051,-72.171501159668],
      ["Harvard Forest","HARV_050",351,"Mixed Forest",42.5377998352051,-72.171501159668],
      ["Fyodorovskoye","fy3",251,"Croplands",56.4476,32.9019],
      ["Fyodorovskoye","Fyodorovskoye",251,"Croplands",56.4476,32.9019],
      ["Fyodorovskoye","fy2",251,"Croplands",56.4476,32.9019],
      ["Fyodorovskoye","fy1",251,"Croplands",56.4476,32.9019],
      ["Cabrieres Avignon","Smos2",142,"Croplands",43.88367,5.16483],
      ["Darabani","Db1",259,"Croplands",48.19477,26.57325],
      ["Toravere","Toravere",76,"Cropland Mosaics",58.2657,26.4659888888889],
      ["Svartberget","Svartberget_CP03",242,"Evergreen Needleleaf",64.26,19.77],
      ["Svartberget","Svartberget_SP20",242,"Evergreen Needleleaf",64.26,19.77],
      ["Svartberget","Svartberget_SP10",242,"Evergreen Needleleaf",64.26,19.77],
      ["Svartberget","Svartberget_SP11",242,"Evergreen Needleleaf",64.26,19.77],
      ["Svartberget","Svartberget_SP12",242,"Evergreen Needleleaf",64.26,19.77],
      ["Svartberget","Svartberget_SP01",242,"Evergreen Needleleaf",64.26,19.77],
      ["Svartberget","Svartberget_SP13",242,"Evergreen Needleleaf",64.26,19.77],
      ["Svartberget","Svartberget_SP02",242,"Evergreen Needleleaf",64.26,19.77],
      ["Svartberget","Svartberget_SP14",242,"Evergreen Needleleaf",64.26,19.77],
      ["Svartberget","Svartberget_SP03",242,"Evergreen Needleleaf",64.26,19.77],
      ["Svartberget","Svartberget_SP15",242,"Evergreen Needleleaf",64.26,19.77],
      ["Svartberget","Svartberget_SP04",242,"Evergreen Needleleaf",64.26,19.77],
      ["Svartberget","Svartberget_SP16",242,"Evergreen Needleleaf",64.26,19.77],
      ["Svartberget","Svartberget_SP05",242,"Evergreen Needleleaf",64.26,19.77],
      ["Svartberget","Svartberget_SP17",242,"Evergreen Needleleaf",64.26,19.77],
      ["Svartberget","Svartberget_SP06",242,"Evergreen Needleleaf",64.26,19.77],
      ["Svartberget","Svartberget_SP18",242,"Evergreen Needleleaf",64.26,19.77],
      ["Svartberget","Svartberget_SP07",242,"Evergreen Needleleaf",64.26,19.77],
      ["Svartberget","Svartberget_SP19",242,"Evergreen Needleleaf",64.26,19.77],
      ["Svartberget","Svartberget_SP08",242,"Evergreen Needleleaf",64.26,19.77],
      ["Svartberget","Svartberget_SP09",242,"Evergreen Needleleaf",64.26,19.77],
      ["Svartberget","Svartberget_CP01",242,"Evergreen Needleleaf",64.26,19.77],
      ["Underc","UNDE_048",518,"Mixed Forest",46.233959,-89.53751],
      ["Underc","UNDE_057",518,"Mixed Forest",46.233959,-89.53751],
      ["Underc","UNDE_045",518,"Mixed Forest",46.233959,-89.53751],
      ["Creon Armagnac","Smos4",149,"Croplands",43.9936,-0.0469],
      ["Salamanca","CasaPeriles",779,"Croplands Mosaics",41.2,-5.36],
      ["Salamanca","LasBrozas",779,"Croplands Mosaics",41.2,-5.36],
      ["Salamanca","LlanosDeLaBoveda",779,"Croplands Mosaics",41.2,-5.36],
      ["Salamanca","Zamarron",779,"Croplands Mosaics",41.2,-5.36],
      ["Salamanca","Canizal",779,"Croplands Mosaics",41.2,-5.36],
      ["Salamanca","LasEritas",779,"Croplands Mosaics",41.2,-5.36],
      ["Salamanca","Guarrati",779,"Croplands Mosaics",41.2,-5.36],
      ["Salamanca","Paredinas",779,"Croplands Mosaics",41.2,-5.36],
      ["Salamanca","LasVacas",779,"Croplands Mosaics",41.2,-5.36],
      ["Salamanca","Carretoro",779,"Croplands Mosaics",41.2,-5.36],
      ["Salamanca","LaCruzDeElias",779,"Croplands Mosaics",41.2,-5.36],
      ["Salamanca","LasTresRayas",779,"Croplands Mosaics",41.2,-5.36],
      ["Salamanca","Granja",779,"Croplands Mosaics",41.2,-5.36],
      ["Salamanca","ConcejoDelMonte",779,"Croplands Mosaics",41.2,-5.36],
      ["Salamanca","ElTomillar",779,"Croplands Mosaics",41.2,-5.36],
      ["Salamanca","LasBodegas",779,"Croplands Mosaics",41.2,-5.36],
      ["Salamanca","LasArenas",779,"Croplands Mosaics",41.2,-5.36],
      ["Salamanca","LasVictorias",779,"Croplands Mosaics",41.2,-5.36],
      ["Salamanca","ElCoto",779,"Croplands Mosaics",41.2,-5.36],
      ["Fort Peck","Fort_Peck_MT",634,"Grasslands",48.3078308105469,-105.101699829102],
      ["Jornada","JORN_055",1329,"Open Shrublands",32.5907,-106.84261],
      ["Jornada","JORN_053",1329,"Open Shrublands",32.5907,-106.84261],
      ["Jornada","JORN_061",1329,"Open Shrublands",32.5907,-106.84261],
      ["Santa Barbara","SantaBarbara",26,"Urban and Built-up",34.4142,-119.8797],
      ["Sodankyla","SO1",195,"Evergreen Needleleaf",67.3671,26.6347],
      ["Sodankyla","SO3",195,"Evergreen Needleleaf",67.3671,26.6347],
      ["Sodankyla","SO2",195,"Evergreen Needleleaf",67.3671,26.6347],
      ["Sodankyla","SO4",195,"Evergreen Needleleaf",67.3671,26.6347],
      ["Blandy Experimental Farm","BLAN_034",183,"Deciduous Broadleaf",39.0602607727051,-78.0716400146484],
      ["Blandy Experimental Farm","BLAN_048",183,"Deciduous Broadleaf",39.0602607727051,-78.0716400146484],
      ["Blandy Experimental Farm","BLAN_052",183,"Deciduous Broadleaf",39.0602607727051,-78.0716400146484],
      ["Tonzi Ranch","t4",177,"Woody Savannas",38.430931,-120.965993],
      ["Tonzi Ranch","t5",177,"Woody Savannas",38.430931,-120.965993],
      ["Tonzi Ranch","t6",177,"Woody Savannas",38.430931,-120.965993],
      ["Tonzi Ranch","t7",177,"Woody Savannas",38.430931,-120.965993],
      ["Tonzi Ranch","t8",177,"Woody Savannas",38.430931,-120.965993],
      ["Tonzi Ranch","t10",177,"Woody Savannas",38.430931,-120.965993],
      ["Tonzi Ranch","t12",177,"Woody Savannas",38.430931,-120.965993],
      ["Tonzi Ranch","t11",177,"Woody Savannas",38.430931,-120.965993],
      ["Tonzi Ranch","t14",177,"Woody Savannas",38.430931,-120.965993],
      ["Tonzi Ranch","t13",177,"Woody Savannas",38.430931,-120.965993],
      ["Tonzi Ranch","t16",177,"Woody Savannas",38.430931,-120.965993],
      ["Tonzi Ranch","t15",177,"Woody Savannas",38.430931,-120.965993],
      ["Tonzi Ranch","t18",177,"Woody Savannas",38.430931,-120.965993],
      ["Tonzi Ranch","t17",177,"Woody Savannas",38.430931,-120.965993],
      ["Tonzi Ranch","t1",177,"Woody Savannas",38.430931,-120.965993],
      ["Tonzi Ranch","t19",177,"Woody Savannas",38.430931,-120.965993],
      ["Tonzi Ranch","TonziRanch",177,"Woody Savannas",38.430931,-120.965993],
      ["Tonzi Ranch","t2",177,"Woody Savannas",38.430931,-120.965993],
      ["Tonzi Ranch","t3",177,"Woody Savannas",38.430931,-120.965993],
      ["Smithsonian Environmental Research Center","SERC_004",15,"Croplands",38.89016,-76.5601],
      ["Smithsonian Environmental Research Center","SERC_016",15,"Croplands",38.89016,-76.5601],
      ["Smithsonian Environmental Research Center","SERC_005",15,"Croplands",38.89016,-76.5601],
      ["Smithsonian Environmental Research Center","SERC_017",15,"Croplands",38.89016,-76.5601],
      ["Smithsonian Environmental Research Center","SERC_006",15,"Croplands",38.89016,-76.5601],
      ["Smithsonian Environmental Research Center","SERC_018",15,"Croplands",38.89016,-76.5601],
      ["Smithsonian Environmental Research Center","SERC_007",15,"Croplands",38.89016,-76.5601],
      ["Smithsonian Environmental Research Center","SERC_019",15,"Croplands",38.89016,-76.5601],
      ["Smithsonian Environmental Research Center","SERC_008",15,"Croplands",38.89016,-76.5601],
      ["Smithsonian Environmental Research Center","SERC_009",15,"Croplands",38.89016,-76.5601],
      ["Smithsonian Environmental Research Center","SERC_053",15,"Croplands",38.89016,-76.5601],
      ["Smithsonian Environmental Research Center","SERC_054",15,"Croplands",38.89016,-76.5601],
      ["Smithsonian Environmental Research Center","SERC_021",15,"Croplands",38.89016,-76.5601],
      ["Smithsonian Environmental Research Center","SERC_010",15,"Croplands",38.89016,-76.5601],
      ["Smithsonian Environmental Research Center","SERC_022",15,"Croplands",38.89016,-76.5601],
      ["Smithsonian Environmental Research Center","SERC_011",15,"Croplands",38.89016,-76.5601],
      ["Smithsonian Environmental Research Center","SERC_012",15,"Croplands",38.89016,-76.5601],
      ["Smithsonian Environmental Research Center","SERC_001",15,"Croplands",38.89016,-76.5601],
      ["Smithsonian Environmental Research Center","SERC_013",15,"Croplands",38.89016,-76.5601],
      ["Smithsonian Environmental Research Center","SERC_002",15,"Croplands",38.89016,-76.5601],
      ["Smithsonian Environmental Research Center","SERC_014",15,"Croplands",38.89016,-76.5601],
      ["Smithsonian Environmental Research Center","SERC_003",15,"Croplands",38.89016,-76.5601],
      ["Smithsonian Environmental Research Center","SERC_061",15,"Croplands",38.89016,-76.5601],
      ["Woodworth","WOOD_027",579,"Grasslands",47.128231048584,-99.2413635253906],
      ["Woodworth","WOOD_005",579,"Grasslands",47.128231048584,-99.2413635253906],
      ["Woodworth","WOOD_004",579,"Grasslands",47.128231048584,-99.2413635253906],
      ["Woodworth","WOOD_069",579,"Grasslands",47.128231048584,-99.2413635253906],
      ["Woodworth","WOOD_058",579,"Grasslands",47.128231048584,-99.2413635253906],
      ["Woodworth","WOOD_025",579,"Grasslands",47.128231048584,-99.2413635253906],
      ["Woodworth","WOOD_003",579,"Grasslands",47.128231048584,-99.2413635253906],
      ["Woodworth","WOOD_024",579,"Grasslands",47.128231048584,-99.2413635253906],
      ["Woodworth","WOOD_013",579,"Grasslands",47.128231048584,-99.2413635253906],
      ["Woodworth","WOOD_002",579,"Grasslands",47.128231048584,-99.2413635253906],
      ["Woodworth","WOOD_009",579,"Grasslands",47.128231048584,-99.2413635253906],
      ["Woodworth","WOOD_008",579,"Grasslands",47.128231048584,-99.2413635253906],
      ["Woodworth","WOOD_029",579,"Grasslands",47.128231048584,-99.2413635253906],
      ["Woodworth","WOOD_007",579,"Grasslands",47.128231048584,-99.2413635253906],
      ["Woodworth","WOOD_006",579,"Grasslands",47.128231048584,-99.2413635253906],
      ["Woodworth","WOOD_023",579,"Grasslands",47.128231048584,-99.2413635253906],
      ["Woodworth","WOOD_001",579,"Grasslands",47.128231048584,-99.2413635253906],
      ["Woodworth","WOOD_022",579,"Grasslands",47.128231048584,-99.2413635253906],
      ["Woodworth","WOOD_011",579,"Grasslands",47.128231048584,-99.2413635253906],
      ["Woodworth","WOOD_021",579,"Grasslands",47.128231048584,-99.2413635253906],
      ["Woodworth","WOOD_010",579,"Grasslands",47.128231048584,-99.2413635253906],
      ["Woodworth","WOOD_064",579,"Grasslands",47.128231048584,-99.2413635253906],
      ["Payerne","Payerne",637,"Evergreen Needleleaf",46.815,6.944]
    ]
  }
}